pyiamvortex/__init__.py
pyiamvortex/cli.py
pyiamvortex/vortex.py
pyiamvortex-0.3.1.dist-info/LICENSE
pyiamvortex-0.3.1.dist-info/METADATA
pyiamvortex-0.3.1.dist-info/WHEEL
pyiamvortex-0.3.1.dist-info/entry_points.txt
pyiamvortex-0.3.1.dist-info/top_level.txt
pyiamvortex-0.3.1.dist-info/RECORD
