Metadata-Version: 2.1
Name: pyiamvortex
Version: 0.3.1
Home-page: https://github.com/joelmccoy/pyiamvortex
Author: Joel McCoy
Author-email: "nbajoel@gmail.com"
License: MIT
Project-URL: Documentation, https://github.com/joelmccoy/pyiamvortex/blob/master/README.md
Project-URL: Issue tracker, https://github.com/joelmccoy/pyiamvortex/issues
Project-URL: Changelog, https://github.com/joelmccoy/pyiamvortex/blob/master/CHANGELOG.md
Keywords: iam aws parser
Classifier: Programming Language :: Python :: 3
Classifier: Programming Language :: Python :: 3.9
Classifier: Programming Language :: Python :: 3.10
Classifier: Programming Language :: Python :: 3.11
Classifier: License :: OSI Approved :: MIT License
Requires-Python: >=3.9
License-File: LICENSE
Requires-Dist: requests
Requires-Dist: typer
Requires-Dist: requests-cache
